fundrives/__init__.py
fundrives/ossutil/__init__.py
fundrives/ossutil/install.py
fundrives/ossutil/post_install.py
fundrive_ossutil-0.1.4.dist-info/METADATA
fundrive_ossutil-0.1.4.dist-info/WHEEL
fundrive_ossutil-0.1.4.dist-info/entry_points.txt
fundrive_ossutil-0.1.4.dist-info/top_level.txt
fundrive_ossutil-0.1.4.dist-info/RECORD
